{
  "db_name": "PostgreSQL",
  "query": "\n            SELECT request_id, user_id, asset, amount, fee, to_address, status, tx_hash, created_at, updated_at\n            FROM withdraw_history\n            WHERE user_id = $1\n            ORDER BY created_at DESC\n            LIMIT 50\n            ",
  "describe": {
    "columns": [
      {
        "ordinal": 0,
        "name": "request_id",
        "type_info": "Varchar"
      },
      {
        "ordinal": 1,
        "name": "user_id",
        "type_info": "Int8"
      },
      {
        "ordinal": 2,
        "name": "asset",
        "type_info": "Varchar"
      },
      {
        "ordinal": 3,
        "name": "amount",
        "type_info": "Int8"
      },
      {
        "ordinal": 4,
        "name": "fee",
        "type_info": "Int8"
      },
      {
        "ordinal": 5,
        "name": "to_address",
        "type_info": "Varchar"
      },
      {
        "ordinal": 6,
        "name": "status",
        "type_info": "Varchar"
      },
      {
        "ordinal": 7,
        "name": "tx_hash",
        "type_info": "Varchar"
      },
      {
        "ordinal": 8,
        "name": "created_at",
        "type_info": "Timestamp"
      },
      {
        "ordinal": 9,
        "name": "updated_at",
        "type_info": "Timestamp"
      }
    ],
    "parameters": {
      "Left": [
        "Int8"
      ]
    },
    "nullable": [
      false,
      false,
      false,
      false,
      false,
      false,
      false,
      true,
      true,
      true
    ]
  },
  "hash": "4120e68be893efb50169da29531af3b45117249433e788bd64ed3b14cf6a0ac3"
}
